LICENSE
MANIFEST.in
README.md
requirements.txt
setup.py
openldapctrl/__init__.py
openldapctrl/cli.py
openldapctrl/services.py
openldapctrl.egg-info/PKG-INFO
openldapctrl.egg-info/SOURCES.txt
openldapctrl.egg-info/dependency_links.txt
openldapctrl.egg-info/entry_points.txt
openldapctrl.egg-info/not-zip-safe
openldapctrl.egg-info/requires.txt
openldapctrl.egg-info/top_level.txt
openldapctrl/data/schema.idsObject.ldif
openldapctrl/data/template.applications.ldif
openldapctrl/data/template.base.ldif
openldapctrl/data/template.change-admin-password.ldif
openldapctrl/data/template.init.ldif
openldapctrl/data/template.namespace.ldif
openldapctrl/data/template.namespace.read.perm.ldif