Metadata-Version: 2.1
Name: openldapctrl
Version: 0.2.9
Summary: Simple command tool to setup openldap server.
Home-page: https://github.com/zencore-cn/zencore-issues
Author: zencore
Author-email: dobetter@zencore.cn
License: MIT
Keywords: ldaputils,openldapctrl
Platform: UNKNOWN
Classifier: Development Status :: 5 - Production/Stable
Classifier: Intended Audience :: Developers
Classifier: Topic :: Software Development :: Libraries :: Python Modules
Classifier: License :: OSI Approved :: MIT License
Classifier: Programming Language :: Python :: 3
Classifier: Programming Language :: Python :: 3 :: Only
